odoo/addons/project_members/README.rst
odoo/addons/project_members/__init__.py
odoo/addons/project_members/__manifest__.py
odoo/addons/project_members/models/__init__.py
odoo/addons/project_members/models/project.py
odoo/addons/project_members/readme/CONTRIBUTORS.rst
odoo/addons/project_members/readme/DESCRIPTION.rst
odoo/addons/project_members/readme/USAGE.rst
odoo/addons/project_members/static/description/icon.png
odoo/addons/project_members/static/description/index.html
odoo/addons/project_members/views/project.xml
odoo12_addon_project_members-12.0.1.0.0.99.dev4.dist-info/METADATA
odoo12_addon_project_members-12.0.1.0.0.99.dev4.dist-info/WHEEL
odoo12_addon_project_members-12.0.1.0.0.99.dev4.dist-info/top_level.txt
odoo12_addon_project_members-12.0.1.0.0.99.dev4.dist-info/RECORD
